dspobjects/__init__.py
dspobjects/backend/__init__.py
dspobjects/backend/num_backend_dispatch.toml
dspobjects/backend/numbackenddispatch.py
dspobjects/dataclasses/__init__.py
dspobjects/dataclasses/dataobjects.py
dspobjects/header.py
dspobjects/operations/__init__.py
dspobjects/operations/iteraxis.py
dspobjects/operations/nanarray.py
dspobjects/plot/__init__.py
dspobjects/plot/bars/__init__.py
dspobjects/plot/bars/barplot.py
dspobjects/plot/bases/__init__.py
dspobjects/plot/bases/baseplot.py
dspobjects/plot/bases/figure.py
dspobjects/plot/bases/plotgroup.py
dspobjects/plot/bases/subplot.py
dspobjects/plot/bases/tracecontainer.py
dspobjects/plot/heatmaps/__init__.py
dspobjects/plot/heatmaps/heatmapplot.py
dspobjects/plot/heatmaps/spectrogramgroup.py
dspobjects/plot/heatmaps/spectrogramplot.py
dspobjects/plot/series/__init__.py
dspobjects/plot/series/performanceplots/__init__.py
dspobjects/plot/series/performanceplots/classifierpreformancegroup.py
dspobjects/plot/series/performanceplots/precisionrecallplot.py
dspobjects/plot/series/performanceplots/rocpercisionrecallgroup.py
dspobjects/plot/series/performanceplots/rocplot.py
dspobjects/plot/series/performanceplots/thresholdperformanceplot.py
dspobjects/plot/series/seriesplot.py
dspobjects/plot/series/stackedseriesplot.py
dspobjects/plot/series/timefreqeuncyplots/__init__.py
dspobjects/plot/series/timefreqeuncyplots/spectraplot.py
dspobjects/plot/series/timefreqeuncyplots/timeseriesplot.py
dspobjects/plot/series/timefreqeuncyplots/timespectragroup.py
dspobjects/plot/series/zeroonedomainplot.py
dspobjects/py.typed
dspobjects/resample.py
dspobjects/time/__init__.py
dspobjects/time/getlocalzone.py
dspobjects/time/nanostamp.py
dspobjects/time/timestamp.py
dspobjects/xlsx/__init__.py
dspobjects/xlsx/xlsxfile.py
dspobjects-0.4.0.dist-info/LICENSE.rst
dspobjects-0.4.0.dist-info/METADATA
dspobjects-0.4.0.dist-info/WHEEL
dspobjects-0.4.0.dist-info/entry_points.txt
dspobjects-0.4.0.dist-info/RECORD
