Metadata-Version: 2.1
Name: dspobjects
Version: 0.4.0
Summary: Objects for digital signal processing.
Home-page: https://github.com/fongant/python-dspobjects
License: MIT
Author: Anthony Fong
Author-email: FongAnthonyM@gmail.com
Requires-Python: >=3.10,<4.0
Classifier: Development Status :: 3 - Alpha
Classifier: License :: OSI Approved :: MIT License
Classifier: Programming Language :: Python :: 3
Classifier: Programming Language :: Python :: 3.10
Classifier: Programming Language :: Python :: 3.11
Requires-Dist: baseobjects (>=1.10.0)
Requires-Dist: click (>=8.0.3)
Requires-Dist: numpy (>=1.24.3)
Requires-Dist: openpyxl (>=3.1.2)
Requires-Dist: pandas (>=1.4.1)
Requires-Dist: plotly (>=5.15.0)
Requires-Dist: tomli (>=2.0.1)
Requires-Dist: xlrd (>=2.0.1)
Project-URL: Changelog, https://github.com/fongant/python-dspobjects/releases
Project-URL: Documentation, https://python-dspobjects.readthedocs.io
Project-URL: Repository, https://github.com/fongant/python-aseobjects
